{
    "bucketName": "provechobetav1p2f26902e4b6c44beab324dec5e82b6d8",
    "authPolicyName": "s3_amplify_304897f9",
    "unauthPolicyName": "s3_amplify_304897f9",
    "authRoleName": {
        "Ref": "AuthRoleName"
    },
    "unauthRoleName": {
        "Ref": "UnauthRoleName"
    },
    "selectedGuestPermissions": [
        "s3:GetObject",
        "s3:ListBucket"
    ],
    "selectedAuthenticatedPermissions": [
        "s3:PutObject",
        "s3:GetObject",
        "s3:ListBucket",
        "s3:DeleteObject"
    ],
    "s3PermissionsAuthenticatedPublic": "s3:PutObject,s3:GetObject,s3:DeleteObject",
    "s3PublicPolicy": "Public_policy_3df0087c",
    "s3PermissionsAuthenticatedUploads": "s3:PutObject",
    "s3UploadsPolicy": "Uploads_policy_3df0087c",
    "s3PermissionsAuthenticatedProtected": "s3:PutObject,s3:GetObject,s3:DeleteObject",
    "s3ProtectedPolicy": "Protected_policy_45cdfae3",
    "s3PermissionsAuthenticatedPrivate": "s3:PutObject,s3:GetObject,s3:DeleteObject",
    "s3PrivatePolicy": "Private_policy_45cdfae3",
    "AuthenticatedAllowList": "ALLOW",
    "s3ReadPolicy": "read_policy_3df0087c",
    "s3PermissionsGuestPublic": "s3:GetObject",
    "s3PermissionsGuestUploads": "DISALLOW",
    "GuestAllowList": "ALLOW",
    "triggerFunction": "NONE"
}